{
	"files": [
		{
			"path": "Anotações/anotacoes.docx",
			"bookmarks": [
				{
					"line": 17,
					"column": 0,
					"label": ""
				},
				{
					"line": 130,
					"column": 0,
					"label": ""
				},
				{
					"line": 436,
					"column": 0,
					"label": ""
				},
				{
					"line": 850,
					"column": 0,
					"label": ""
				},
				{
					"line": 913,
					"column": 0,
					"label": ""
				},
				{
					"line": 949,
					"column": 0,
					"label": ""
				},
				{
					"line": 995,
					"column": 0,
					"label": ""
				}
			]
		}
	]
}